README.txt
setup.py
imhotep_flake8/__init__.py
imhotep_flake8/plugin.py
imhotep_flake8.egg-info/PKG-INFO
imhotep_flake8.egg-info/SOURCES.txt
imhotep_flake8.egg-info/dependency_links.txt
imhotep_flake8.egg-info/entry_points.txt
imhotep_flake8.egg-info/requires.txt
imhotep_flake8.egg-info/top_level.txt