Metadata-Version: 1.0
Name: imhotep-flake8
Version: 0.2.1
Summary: An imhotep plugin for flake8 validation.
Home-page: https://github.com/glogiotatidis/imhotep_flake8
Author: Giorgos Logiotatidis
Author-email: giorgos@mozilla.com
License: UNKNOWN
Keywords: testing,imhotep
Platform: UNKNOWN
